telegen_definitions/__init__.py
telegen_definitions/__main__.py
telegen_definitions/endpoints.py
telegen_definitions/generated.py
telegen_definitions/multipart_encoder.py
telegen_definitions/types.py
telegen_definitions-4.9.1.0.8.dist-info/METADATA
telegen_definitions-4.9.1.0.8.dist-info/WHEEL
telegen_definitions-4.9.1.0.8.dist-info/top_level.txt
telegen_definitions-4.9.1.0.8.dist-info/RECORD
