Metadata-Version: 2.1
Name: telegen-definitions
Version: 4.9.1.0.8
Summary: Autogenerated telegen definitions
Home-page: https://gitlab.com/strychnide/telegen
Author: Alessandro Cerruti
Author-email: strychnide@protonmail.com
License: UNKNOWN
Project-URL: Documentation, https://strychnide.gitlab.io/telegen
Project-URL: Issues, https://gitlab.com/strychnide/telegen/-/issues
Project-URL: Source, https://gitlab.com/strychnide/telegen
Platform: UNKNOWN
Classifier: Environment :: Console
Classifier: Intended Audience :: Developers
Classifier: License :: OSI Approved :: MIT License
Classifier: Operating System :: OS Independent
Classifier: Programming Language :: Python :: 3.6
Classifier: Programming Language :: Python :: 3.7
Classifier: Programming Language :: Python :: 3.8
Classifier: Topic :: Communications :: Chat
Classifier: Topic :: Internet
Classifier: Topic :: Software Development :: Libraries :: Python Modules
Requires-Python: >=3.6
